neurtu/__init__.py
neurtu/base.py
neurtu/delayed.py
neurtu/metrics.py
neurtu/utils.py
neurtu/externals/__init__.py
neurtu/externals/shutil_which.py
neurtu/tests/__init__.py
neurtu/tests/test_benchmark.py
neurtu/tests/test_delayed.py
neurtu/tests/test_utils.py
neurtu-0.3.0.dist-info/LICENSE
neurtu-0.3.0.dist-info/METADATA
neurtu-0.3.0.dist-info/WHEEL
neurtu-0.3.0.dist-info/top_level.txt
neurtu-0.3.0.dist-info/RECORD
