Metadata-Version: 2.1
Name: neurtu
Version: 0.3.0
Summary: A simple benchmarking tool
Home-page: https://github.com/symerio/neurtu
Author: Roman Yurchak
Author-email: roman.yurchak@symerio.com
License: BSD
Platform: UNKNOWN
Classifier: Development Status :: 4 - Beta
Classifier: Intended Audience :: Science/Research
Classifier: Intended Audience :: Developers
Classifier: License :: OSI Approved :: BSD License
Classifier: Programming Language :: Python
Classifier: Programming Language :: Python :: 2
Classifier: Programming Language :: Python :: 2.7
Classifier: Programming Language :: Python :: 3
Classifier: Programming Language :: Python :: 3.4
Classifier: Programming Language :: Python :: 3.5
Classifier: Programming Language :: Python :: 3.6
Classifier: Topic :: Software Development
Classifier: Operating System :: POSIX
Classifier: Operating System :: Unix
Requires-Dist: memory-profiler
Requires-Dist: psutil
Requires-Dist: tqdm
